setup.cfg
setup.py
coinsbill/__init__.py
coinsbill/base.py
coinsbill/client.py
coinsbill/helper.py
coinsbill/resource.py
coinsbill.egg-info/PKG-INFO
coinsbill.egg-info/SOURCES.txt
coinsbill.egg-info/dependency_links.txt
coinsbill.egg-info/requires.txt
coinsbill.egg-info/top_level.txt