Metadata-Version: 1.1
Name: coinsbill
Version: 1.0
Summary: Python interaction with the CoinsBill API.
Home-page: https://www.coinsbill.com/developers
Author: CoinsBill
Author-email: support@coinsbill.com
License: Apache License, Version 2.0, January 2004
Keywords: coinsbill,bitcoin,payment
Platform: UNKNOWN
Classifier: Development Status :: 4 - Beta
Classifier: Environment :: Console
Classifier: Environment :: Web Environment
Classifier: Intended Audience :: End Users/Desktop
Classifier: Intended Audience :: Developers
Classifier: Operating System :: OS Independent
Classifier: Programming Language :: Python
Classifier: Topic :: Internet
Classifier: Topic :: Software Development :: Libraries :: Python Modules
